{
  "0": "personamem_32k_persona_0",
  "1": "personamem_32k_persona_1",
  "2": "personamem_32k_persona_2",
  "3": "personamem_32k_persona_3",
  "4": "personamem_32k_persona_4",
  "5": "personamem_32k_persona_5",
  "6": "personamem_32k_persona_6",
  "7": "personamem_32k_persona_7",
  "8": "personamem_32k_persona_8",
  "9": "personamem_32k_persona_9",
  "10": "personamem_32k_persona_10",
  "11": "personamem_32k_persona_11",
  "12": "personamem_32k_persona_12",
  "13": "personamem_32k_persona_13",
  "14": "personamem_32k_persona_14",
  "15": "personamem_32k_persona_15",
  "16": "personamem_32k_persona_16",
  "17": "personamem_32k_persona_17",
  "18": "personamem_32k_persona_18",
  "19": "personamem_32k_persona_19"
}